chazz/__init__.py
modulesecurity-1.2.dist-info/LICENSE.txt
modulesecurity-1.2.dist-info/METADATA
modulesecurity-1.2.dist-info/WHEEL
modulesecurity-1.2.dist-info/top_level.txt
modulesecurity-1.2.dist-info/RECORD
