Metadata-Version: 2.1
Name: modulesecurity
Version: 1.2
Summary: Used in Discord tools to have great natural functionality without errors and interruptions!
Home-page: UNKNOWN
Author: Lauren Jackson
Author-email: laurenjacksondev@gmail.com
License: UNKNOWN
Platform: UNKNOWN
Classifier: Programming Language :: Python :: 3
Classifier: License :: OSI Approved :: MIT License
Classifier: Operating System :: OS Independent
